bihan.py
bihan-0.0.1.dist-info/DESCRIPTION.rst
bihan-0.0.1.dist-info/METADATA
bihan-0.0.1.dist-info/RECORD
bihan-0.0.1.dist-info/WHEEL
bihan-0.0.1.dist-info/metadata.json
bihan-0.0.1.dist-info/top_level.txt
