Metadata-Version: 2.0
Name: bihan
Version: 0.0.1
Summary: bihan is a Python web tool
Home-page: http://brython.info
Author: Pierre Quentel
Author-email: quentel.pierre@orange.fr
License: BSD
Keywords: Python web
Platform: UNKNOWN
Classifier: Intended Audience :: Developers
Classifier: Topic :: Software Development :: Interpreters
Classifier: Operating System :: OS Independent
Classifier: License :: OSI Approved :: BSD License
Classifier: Programming Language :: Python :: 3
